sensortower_mcp/__init__.py
sensortower_mcp/base.py
sensortower_mcp/config.py
sensortower_mcp/documentation.py
sensortower_mcp/prompts.py
sensortower_mcp/server.py
sensortower_mcp/tool_examples.py
sensortower_mcp/tools/__init__.py
sensortower_mcp/tools/app_analysis.py
sensortower_mcp/tools/market_analysis.py
sensortower_mcp/tools/search_discovery.py
sensortower_mcp/tools/store_marketing.py
sensortower_mcp/tools/utilities.py
sensortower_mcp/tools/your_metrics.py
sensortower_mcp-1.2.10.dist-info/METADATA
sensortower_mcp-1.2.10.dist-info/WHEEL
sensortower_mcp-1.2.10.dist-info/entry_points.txt
sensortower_mcp-1.2.10.dist-info/RECORD
