Metadata-Version: 2.4
Name: sensortower-mcp
Version: 1.2.10
Summary: Model Context Protocol server for Sensor Tower APIs using FastMCP
Requires-Python: >=3.10
Requires-Dist: fastmcp>=2.12.4
Requires-Dist: httpx>=0.25.0
Requires-Dist: python-dotenv>=1.0.0
Provides-Extra: test
Requires-Dist: aiohttp>=3.10.0; extra == 'test'
Requires-Dist: pyyaml>=6.0; extra == 'test'
